OCTOPUS/ORC.py
OCTOPUS/__init__.py
OCTOPUS/field_map_exp.py
OCTOPUS/load_fieldmap.py
OCTOPUS/prog.py
OCTOPUS/fieldmap/__init__.py
OCTOPUS/fieldmap/simulate.py
OCTOPUS/fieldmap/unwrap.py
OCTOPUS/recon/__init__.py
OCTOPUS/recon/imtransforms.py
OCTOPUS/recon/rawdata_recon.py
OCTOPUS/utils/__init__.py
OCTOPUS/utils/dataio.py
OCTOPUS/utils/metrics.py
OCTOPUS/utils/plotting.py
MR_OCTOPUS-0.2.7.dist-info/LICENSE
MR_OCTOPUS-0.2.7.dist-info/METADATA
MR_OCTOPUS-0.2.7.dist-info/WHEEL
MR_OCTOPUS-0.2.7.dist-info/entry_points.txt
MR_OCTOPUS-0.2.7.dist-info/top_level.txt
MR_OCTOPUS-0.2.7.dist-info/RECORD
