Metadata-Version: 2.1
Name: MR-OCTOPUS
Version: 0.2.7
Summary: Off-resonance correction of MR images
Home-page: https://github.com/imr-framework/OCTOPUS
Author: Marina Manso Jimeno
Author-email: mm5290@columbia.edu
License: License :: OSI Approved :: GNU Affero General Public License v3
Platform: UNKNOWN
Classifier: Programming Language :: Python :: 3.6
Classifier: Programming Language :: Python :: 3.7
Classifier: License :: OSI Approved :: GNU Affero General Public License v3
Classifier: Operating System :: OS Independent
Requires-Dist: matplotlib (>=3.1.3)
Requires-Dist: nibabel (>=3.0.2)
Requires-Dist: numpy (>=1.18.1)
Requires-Dist: opencv-python (>=4.1.2.30)
Requires-Dist: pydicom (>=2.0.0)
Requires-Dist: pynufft (==2019.2.3)
Requires-Dist: scikit-image (>=0.16.2)
Requires-Dist: scipy (==1.4.1)
